litedfs/__init__.py
litedfs/version.py
litedfs/data/README.md
litedfs/data/__init__.py
litedfs/data/config.py
litedfs/data/configuration.yml.temp
litedfs/data/data.py
litedfs/data/data.sh
litedfs/data/install_systemd_service.sh
litedfs/data/litedfs-data.service.temp
litedfs/data/logger.py
litedfs/data/uninstall_systemd_service.sh
litedfs/data/handlers/__init__.py
litedfs/data/handlers/base.py
litedfs/data/handlers/data.py
litedfs/data/handlers/info.py
litedfs/data/utils/__init__.py
litedfs/data/utils/common.py
litedfs/data/utils/persistent_config.py
litedfs/data/utils/registrant.py
litedfs/data/utils/task_cache.py
litedfs/data/utils/task_processer.py
litedfs/name/README.md
litedfs/name/__init__.py
litedfs/name/config.py
litedfs/name/configuration.yml.temp
litedfs/name/install_systemd_service.sh
litedfs/name/litedfs-name.service.temp
litedfs/name/logger.py
litedfs/name/name.py
litedfs/name/name.sh
litedfs/name/uninstall_systemd_service.sh
litedfs/name/db/__init__.py
litedfs/name/db/sqlite_interface.py
litedfs/name/handlers/__init__.py
litedfs/name/handlers/base.py
litedfs/name/handlers/data.py
litedfs/name/handlers/info.py
litedfs/name/models/__init__.py
litedfs/name/models/data_nodes.py
litedfs/name/utils/__init__.py
litedfs/name/utils/append_log.py
litedfs/name/utils/common.py
litedfs/name/utils/fs_core.py
litedfs/name/utils/listener.py
litedfs/name/utils/persistent_config.py
litedfs/tool/__init__.py
litedfs/tool/client.py
litedfs/tool/litedfs.py
litedfs-0.0.3.dist-info/METADATA
litedfs-0.0.3.dist-info/WHEEL
litedfs-0.0.3.dist-info/entry_points.txt
litedfs-0.0.3.dist-info/top_level.txt
litedfs-0.0.3.dist-info/RECORD
