Metadata-Version: 2.1
Name: litedfs
Version: 0.0.3
Summary: LiteDFS: distributed file system
Home-page: https://github.com/fiefdx/LiteDFS
Author: fiefdx
Author-email: fiefdx@163.com
License: MIT
Platform: UNKNOWN
Classifier: License :: OSI Approved :: MIT License
Classifier: Programming Language :: Python :: 3
Classifier: Programming Language :: Python :: 3.7
Requires-Dist: requests (>=2.22.0)
Requires-Dist: tornado
Requires-Dist: pyYAML
Requires-Dist: tinydb
Requires-Dist: sqlalchemy
Requires-Dist: tornado-discovery
